LICENSE
MANIFEST.in
README.md
requirements.txt
setup.py
cget/__init__.py
cget/builder.py
cget/cli.py
cget/package.py
cget/prefix.py
cget/types.py
cget/util.py
cget.egg-info/PKG-INFO
cget.egg-info/SOURCES.txt
cget.egg-info/dependency_links.txt
cget.egg-info/entry_points.txt
cget.egg-info/not-zip-safe
cget.egg-info/requires.txt
cget.egg-info/top_level.txt
cget/cmake/autotools.cmake
cget/cmake/binary.cmake
cget/cmake/boost.cmake
cget/cmake/header.cmake
cget/cmake/meson.cmake
cget/cmake/subdir.cmake
test/test_cget.py