Metadata-Version: 1.0
Name: cget
Version: 0.1.7
Summary: Cmake package retrieval
Home-page: https://github.com/pfultz2/cget
Author: Paul Fultz II
Author-email: pfultz2@yahoo.com
License: boost
Platform: UNKNOWN
